CHANGELOG
COPYRIGHT
LICENSE
MANIFEST.in
README
setup.py
doc/Makefile
doc/conf.py
doc/index.rst
sphinxcontrib/__init__.py
sphinxcontrib/trydoc/Makefile.template
sphinxcontrib/trydoc/__init__.py
sphinxcontrib/trydoc/conf.py.template
sphinxcontrib/trydoc/index.rst.es.template
sphinxcontrib/trydoc/quickstart.py
sphinxcontrib/trydoc/symlinks.py
sphinxcontrib/trydoc/update_modules.py
trydoc.egg-info/PKG-INFO
trydoc.egg-info/SOURCES.txt
trydoc.egg-info/dependency_links.txt
trydoc.egg-info/entry_points.txt
trydoc.egg-info/namespace_packages.txt
trydoc.egg-info/not-zip-safe
trydoc.egg-info/pbr.json
trydoc.egg-info/requires.txt
trydoc.egg-info/top_level.txt