Metadata-Version: 1.1
Name: trydoc
Version: 0.8
Summary: Tryton markup for Sphinx
Home-page: https://bitbucket.org/nantic/trydoc
Author: NaN Projectes de Programari Lliure, S.L.
Author-email: info@nan-tic.com
License: BSD
Download-URL: http://pypi.python.org/pypi/trydoc
Platform: any
Classifier: Development Status :: 3 - Alpha
Classifier: Environment :: Console
Classifier: Environment :: Web Environment
Classifier: Intended Audience :: Developers
Classifier: License :: OSI Approved :: BSD License
Classifier: Operating System :: OS Independent
Classifier: Programming Language :: Python
Classifier: Topic :: Documentation
Classifier: Topic :: Utilities
